bcb/__init__.py
bcb/currency.py
bcb/odata/__init__.py
bcb/odata/api.py
bcb/odata/framework.py
bcb/sgs.py
bcb/utils.py
python_bcb-0.3.0.dist-info/LICENSE
python_bcb-0.3.0.dist-info/METADATA
python_bcb-0.3.0.dist-info/WHEEL
python_bcb-0.3.0.dist-info/RECORD
