Metadata-Version: 2.1
Name: python-bcb
Version: 0.3.0
Summary: 
Author: wilsonfreitas
Author-email: wilson.freitas@gmail.com
Requires-Python: >=3.10
Classifier: Programming Language :: Python :: 3
Classifier: Programming Language :: Python :: 3.10
Classifier: Programming Language :: Python :: 3.11
Classifier: Programming Language :: Python :: 3.12
Requires-Dist: httpx (>=0.24.0)
Requires-Dist: lxml (>=4.9.2)
Requires-Dist: pandas (>=2.0.0)
Requires-Dist: requests (>=2.31.0)
